aiopusher/__init__.py
aiopusher-0.1.0.dist-info/LICENSE
aiopusher-0.1.0.dist-info/METADATA
aiopusher-0.1.0.dist-info/WHEEL
aiopusher-0.1.0.dist-info/RECORD
