Metadata-Version: 2.1
Name: aiopusher
Version: 0.1.0
Summary: An async client for Pusher. Currently in development. Is unusable at the moment.
Home-page: https://github.com/Cikmo/pusher-client
License: MIT
Author: Christian
Author-email: contact@komodo.link
Requires-Python: >=3.8,<4.0
Classifier: License :: OSI Approved :: MIT License
Classifier: Programming Language :: Python :: 3
Classifier: Programming Language :: Python :: 3.8
Classifier: Programming Language :: Python :: 3.9
Classifier: Programming Language :: Python :: 3.10
Classifier: Programming Language :: Python :: 3.11
Project-URL: Repository, https://github.com/Cikmo/pusher-client
